django_hey/__init__.py
django_hey/hey.py
django_hey-0.1.10.dist-info/LICENSE
django_hey-0.1.10.dist-info/METADATA
django_hey-0.1.10.dist-info/WHEEL
django_hey-0.1.10.dist-info/entry_points.txt
django_hey-0.1.10.dist-info/top_level.txt
django_hey-0.1.10.dist-info/RECORD
